infer/__init__.py
infer/common/__init__.py
infer/common/exceptions.py
infer/common/utils.py
infer/cpp/CMakeLists.txt
infer/cpp/__init__.py
infer/cpp/inference/CMakeLists.txt
infer/cpp/inference/__init__.py
infer/cpp/inference/config.h
infer/cpp/inference/exceptions.h
infer/cpp/inference/inference.h
infer/cpp/inference/macros.h
infer/cpp/inference/preprocess.h
infer/cpp/inference/utils.h
infer/cpp/inference/graph/graph.h
infer/cpp/inference/graph/implicit_tensors.h
infer/cpp/inference/graph/method_graphs.h
infer/cpp/inference/passes/fuse_list_ops.h
infer/cpp/inference/passes/inliner.h
infer/cpp/inference/passes/loop_unrolling.h
infer/cpp/inference/passes/lower_block_lists.h
infer/cpp/inference/passes/lower_block_tuples.h
infer/cpp/inference/passes/pass_utils.h
infer/cpp/inference/passes/passes.h
infer/cpp/inference/quantization/disjoint_set.h
infer/cpp/inference/quantization/observer.h
infer/cpp/inference/quantization/observer_utils.h
infer/cpp/inference/quantization/params.h
infer/cpp/inference/quantization/quantization.h
infer/cpp/inference/quantization/range_observer.h
infer/cpp/inference/quantization/shape_observer.h
infer/cpp/inference/quantization/stats.h
infer/cpp/torch_ops/CMakeLists.txt
infer/cpp/torch_ops/__init__.py
infer/cpp/torch_ops/torch_ops.h
infer/cpp/torch_ops/ops/nucleus_sampling.h
infer/postprocess/__init__.py
infer/postprocess/generate.py
infer/postprocess/graph.py
infer/postprocess/handler.py
infer/postprocess/compilers/__init__.py
infer/postprocess/compilers/auto.py
infer/postprocess/compilers/base.py
infer/postprocess/compilers/utils.py
infer/postprocess/compilers/_coreml/__init__.py
infer/postprocess/compilers/_coreml/compiler.py
infer/postprocess/compilers/_coreml/engine.py
infer/postprocess/compilers/_tensorrt/__init__.py
infer/postprocess/compilers/_tensorrt/compiler.py
infer/postprocess/compilers/_tensorrt/engine.py
infer/postprocess/compilers/_tensorrt/utils.py
infer/postprocess/handlers/__init__.py
ml_infer-0.0.3.dist-info/METADATA
ml_infer-0.0.3.dist-info/WHEEL
ml_infer-0.0.3.dist-info/top_level.txt
ml_infer-0.0.3.dist-info/RECORD
